grimoire_elk/__init__.py
grimoire_elk/_version.py
grimoire_elk/elastic.py
grimoire_elk/elastic_analyzer.py
grimoire_elk/elastic_items.py
grimoire_elk/elastic_mapping.py
grimoire_elk/elk.py
grimoire_elk/enriched/__init__.py
grimoire_elk/enriched/askbot.py
grimoire_elk/enriched/bugzilla.py
grimoire_elk/enriched/bugzillarest.py
grimoire_elk/enriched/ceres_base.py
grimoire_elk/enriched/cocom.py
grimoire_elk/enriched/colic.py
grimoire_elk/enriched/confluence.py
grimoire_elk/enriched/crates.py
grimoire_elk/enriched/discourse.py
grimoire_elk/enriched/dockerdeps.py
grimoire_elk/enriched/dockerhub.py
grimoire_elk/enriched/dockersmells.py
grimoire_elk/enriched/enrich.py
grimoire_elk/enriched/functest.py
grimoire_elk/enriched/gerrit.py
grimoire_elk/enriched/git.py
grimoire_elk/enriched/github.py
grimoire_elk/enriched/github2.py
grimoire_elk/enriched/github_study_evolution.py
grimoire_elk/enriched/githubql.py
grimoire_elk/enriched/gitlab.py
grimoire_elk/enriched/gitter.py
grimoire_elk/enriched/google_hits.py
grimoire_elk/enriched/graal_study_evolution.py
grimoire_elk/enriched/groupsio.py
grimoire_elk/enriched/hyperkitty.py
grimoire_elk/enriched/jenkins.py
grimoire_elk/enriched/jira.py
grimoire_elk/enriched/kitsune.py
grimoire_elk/enriched/launchpad.py
grimoire_elk/enriched/mappings/git_aoc.json
grimoire_elk/enriched/mappings/git_aoc_es7.json
grimoire_elk/enriched/mappings/onion.json
grimoire_elk/enriched/mappings/onion_es7.json
grimoire_elk/enriched/mattermost.py
grimoire_elk/enriched/mbox.py
grimoire_elk/enriched/mbox_study_kip.py
grimoire_elk/enriched/mediawiki.py
grimoire_elk/enriched/meetup.py
grimoire_elk/enriched/mozillaclub.py
grimoire_elk/enriched/nntp.py
grimoire_elk/enriched/pagure.py
grimoire_elk/enriched/phabricator.py
grimoire_elk/enriched/pipermail.py
grimoire_elk/enriched/puppetforge.py
grimoire_elk/enriched/redmine.py
grimoire_elk/enriched/remo.py
grimoire_elk/enriched/rocketchat.py
grimoire_elk/enriched/rss.py
grimoire_elk/enriched/slack.py
grimoire_elk-1.7.0.dist-info/METADATA
grimoire_elk-1.7.0.dist-info/WHEEL
grimoire_elk-1.7.0.dist-info/entry_points.txt
grimoire_elk-1.7.0.dist-info/licenses/AUTHORS
grimoire_elk-1.7.0.dist-info/licenses/LICENSE
grimoire_elk-1.7.0.dist-info/RECORD
