Metadata-Version: 2.4
Name: grimoire-elk
Version: 1.7.0
Summary: GrimoireELK processes and stores software development data to ElasticSearch
License: GPL-3.0-or-later
License-File: AUTHORS
License-File: LICENSE
Keywords: development repositories analytics
Author: GrimoireLab Developers
Requires-Python: >=3.10,<4.0
Classifier: Development Status :: 5 - Production/Stable
Classifier: Intended Audience :: Developers
Classifier: License :: OSI Approved :: GNU General Public License v3 or later (GPLv3+)
Classifier: Programming Language :: Python :: 3
Classifier: Programming Language :: Python :: 3.10
Classifier: Programming Language :: Python :: 3.11
Classifier: Programming Language :: Python :: 3.12
Classifier: Programming Language :: Python :: 3.13
Classifier: Programming Language :: Python :: 3.14
Classifier: Topic :: Software Development
Requires-Dist: cereslib (>=0.3)
Requires-Dist: geopy (>=2.0.0,<3.0.0)
Requires-Dist: graal (>=0.3)
Requires-Dist: grimoirelab-toolkit (>=0.3)
Requires-Dist: opensearch-py (>=3.0.0,<4.0.0)
Requires-Dist: pandas (>=0.22,<3)
Requires-Dist: perceval (>=0.19)
Requires-Dist: perceval-mozilla (>=0.3)
Requires-Dist: perceval-opnfv (>=0.2)
Requires-Dist: perceval-puppet (>=0.2)
Requires-Dist: perceval-weblate (>=0.2)
Requires-Dist: requests (>=2.7.0,<3.0.0)
Requires-Dist: sortinghat (>=0.7.20)
Requires-Dist: statsmodels (>=0.9.0)
Requires-Dist: urllib3 (>=1.26,<3)
Project-URL: Bug Tracker, https://github.com/chaoss/grimoirelab-elk/issues
Project-URL: Repository, https://github.com/chaoss/grimoirelab-elk
